stock_analysis/__init__.py
stock_analysis/comparison_analysis.py
stock_analysis/moving_averages.py
stock_analysis/performance_metrics.py
stock_analysis/trend_analysis.py
stock_analysis/volatility_analysis.py
stock_analysis/volume_analysis.py
tests/__init__.py
tests/test_comparison_analysis.py
tests/test_moving_averages.py
tests/test_performance_metrics.py
tests/test_trend_analysis.py
tests/test_volatility_analysis.py
tests/test_volume_analysis.py
tests/__pycache__/__init__.cpython-38.pyc
tests/__pycache__/test_comparison_analysis.cpython-38-pytest-8.2.0.pyc
tests/__pycache__/test_moving_averages.cpython-38-pytest-8.2.0.pyc
tests/__pycache__/test_performance_metrics.cpython-38-pytest-8.2.0.pyc
tests/__pycache__/test_trend_analysis.cpython-38-pytest-8.2.0.pyc
tests/__pycache__/test_volatility_analysis.cpython-38-pytest-8.2.0.pyc
tests/__pycache__/test_volume_analysis.cpython-38-pytest-8.2.0.pyc
stock_analysis_package-0.2.0.dist-info/LICENSE
stock_analysis_package-0.2.0.dist-info/METADATA
stock_analysis_package-0.2.0.dist-info/WHEEL
stock_analysis_package-0.2.0.dist-info/entry_points.txt
stock_analysis_package-0.2.0.dist-info/top_level.txt
stock_analysis_package-0.2.0.dist-info/RECORD
