Metadata-Version: 2.1
Name: stock-analysis-package
Version: 0.2.0
Summary: A small python package for stock market analysis
Home-page: https://github.com/samhith-raj/stock_analysis_package
Author: Samhith Raj
Author-email: ssaneboi@stevens.edu
Classifier: Programming Language :: Python :: 3
Classifier: License :: OSI Approved :: MIT License
Classifier: Operating System :: OS Independent
Requires-Python: >=3.6
License-File: LICENSE
Requires-Dist: numpy
Requires-Dist: pandas
Requires-Dist: matplotlib
Requires-Dist: scipy
Requires-Dist: yfinance
